viv_compiler/__init__.py
viv_compiler/__main__.py
viv_compiler/_version.py
viv_compiler/api.py
viv_compiler/cli.py
viv_compiler/py.typed
viv_compiler/_samples/__init__.py
viv_compiler/_samples/smoke-test.viv
viv_compiler/backports/__init__.py
viv_compiler/backports/backports.py
viv_compiler/config/__init__.py
viv_compiler/config/config.py
viv_compiler/core/__init__.py
viv_compiler/core/core.py
viv_compiler/core/includes.py
viv_compiler/core/metadata.py
viv_compiler/core/postprocessing.py
viv_compiler/core/validation.py
viv_compiler/core/visitor.py
viv_compiler/grammar/__init__.py
viv_compiler/grammar/viv.peg
viv_compiler/types/__init__.py
viv_compiler/types/content_public_schemas.py
viv_compiler/types/dsl_public_schemas.py
viv_compiler/types/internal_types.py
viv_compiler/utils/__init__.py
viv_compiler/utils/utils.py
viv_compiler-0.1.2.dist-info/licenses/LICENSE
viv_compiler-0.1.2.dist-info/METADATA
viv_compiler-0.1.2.dist-info/WHEEL
viv_compiler-0.1.2.dist-info/entry_points.txt
viv_compiler-0.1.2.dist-info/top_level.txt
viv_compiler-0.1.2.dist-info/RECORD
