Metadata-Version: 2.4
Name: viv-compiler
Version: 0.1.2
Summary: Compiler for the DSL of Viv, an action system for emergent narrative.
Author-email: James Ryan <mail@jamesryan.ai>
License: MIT License
Project-URL: Homepage, https://github.com/james-owen-ryan/viv
Project-URL: Repository, https://github.com/james-owen-ryan/viv/tree/main/compiler
Project-URL: Issues, https://github.com/james-owen-ryan/viv/issues
Classifier: License :: OSI Approved :: MIT License
Classifier: Programming Language :: Python :: 3 :: Only
Classifier: Programming Language :: Python :: 3.10
Classifier: Programming Language :: Python :: 3.11
Classifier: Programming Language :: Python :: 3.12
Classifier: Topic :: Software Development :: Compilers
Requires-Python: >=3.10
License-File: LICENSE
Requires-Dist: arpeggio<3.0,>=2.0
Requires-Dist: pydantic<2.12,>=2.11
Requires-Dist: typing_extensions<5.0,>=4.6
Dynamic: license-file
